fastapi_sql/__init__.py
fastapi_sql/middleware.py
fastapi_sql/migrate.py
fastapi_sql/model.py
fastapi_sql/table.py
fastapi_sql-0.3.7.dist-info/METADATA
fastapi_sql-0.3.7.dist-info/WHEEL
fastapi_sql-0.3.7.dist-info/RECORD
