Metadata-Version: 2.1
Name: fastapi-sql
Version: 0.3.7
Summary: 
Author: Michael Piccirillo
Author-email: 70709374+Khrysys@users.noreply.github.com
Requires-Python: >=3.8,<4.0
Classifier: Programming Language :: Python :: 3
Classifier: Programming Language :: Python :: 3.8
Classifier: Programming Language :: Python :: 3.9
Classifier: Programming Language :: Python :: 3.10
Classifier: Programming Language :: Python :: 3.11
Requires-Dist: SQLAlchemy (>=2.0.10,<3.0.0)
Requires-Dist: alembic (>=1.10.4,<2.0.0)
Requires-Dist: asyncpg (>=0.27.0,<0.28.0)
Requires-Dist: fastapi (>=0.95.1,<0.96.0)
